[
  {
    "id": 710114,
    "province_id": 71,
    "regency_id": 7101,
    "district_id": 710114,
    "value": "Abak",
    "postal_code": "95737"
  },
  {
    "id": 710114,
    "province_id": 71,
    "regency_id": 7101,
    "district_id": 710114,
    "value": "Bakan",
    "postal_code": "95737"
  },
  {
    "id": 710114,
    "province_id": 71,
    "regency_id": 7101,
    "district_id": 710114,
    "value": "Bombanon",
    "postal_code": "95737"
  },
  {
    "id": 710114,
    "province_id": 71,
    "regency_id": 7101,
    "district_id": 710114,
    "value": "Kopandakan II",
    "postal_code": "95737"
  },
  {
    "id": 710114,
    "province_id": 71,
    "regency_id": 7101,
    "district_id": 710114,
    "value": "Lolayan",
    "postal_code": "95737"
  },
  {
    "id": 710114,
    "province_id": 71,
    "regency_id": 7101,
    "district_id": 710114,
    "value": "Matali Baru",
    "postal_code": "95737"
  },
  {
    "id": 710114,
    "province_id": 71,
    "regency_id": 7101,
    "district_id": 710114,
    "value": "Mengkang",
    "postal_code": "95737"
  },
  {
    "id": 710114,
    "province_id": 71,
    "regency_id": 7101,
    "district_id": 710114,
    "value": "Mopait",
    "postal_code": "95737"
  },
  {
    "id": 710114,
    "province_id": 71,
    "regency_id": 7101,
    "district_id": 710114,
    "value": "Mopusi",
    "postal_code": "95737"
  },
  {
    "id": 710114,
    "province_id": 71,
    "regency_id": 7101,
    "district_id": 710114,
    "value": "Sanoyan Selatan (Tanoyan Selatan)",
    "postal_code": "95737"
  },
  {
    "id": 710114,
    "province_id": 71,
    "regency_id": 7101,
    "district_id": 710114,
    "value": "Tanoyan Utara",
    "postal_code": "95737"
  },
  {
    "id": 710114,
    "province_id": 71,
    "regency_id": 7101,
    "district_id": 710114,
    "value": "Tapa Aog",
    "postal_code": "95737"
  },
  {
    "id": 710114,
    "province_id": 71,
    "regency_id": 7101,
    "district_id": 710114,
    "value": "Tungoi I",
    "postal_code": "95737"
  },
  {
    "id": 710114,
    "province_id": 71,
    "regency_id": 7101,
    "district_id": 710114,
    "value": "Tungoi II",
    "postal_code": "95737"
  }
]