[
  {
    "id": 531118,
    "province_id": 53,
    "regency_id": 5311,
    "district_id": 531118,
    "value": "BidiPraing",
    "postal_code": "87151"
  },
  {
    "id": 531118,
    "province_id": 53,
    "regency_id": 5311,
    "district_id": 531118,
    "value": "Kangeli",
    "postal_code": "87151"
  },
  {
    "id": 531118,
    "province_id": 53,
    "regency_id": 5311,
    "district_id": 531118,
    "value": "Laihau (Laihawu)",
    "postal_code": "87151"
  },
  {
    "id": 531118,
    "province_id": 53,
    "regency_id": 5311,
    "district_id": 531118,
    "value": "Mondulambi (Mondu Lambi)",
    "postal_code": "87151"
  },
  {
    "id": 531118,
    "province_id": 53,
    "regency_id": 5311,
    "district_id": 531118,
    "value": "Umamanu",
    "postal_code": "87151"
  },
  {
    "id": 531118,
    "province_id": 53,
    "regency_id": 5311,
    "district_id": 531118,
    "value": "Watumbelar",
    "postal_code": "87151"
  }
]