[
  {
    "id": 331420,
    "province_id": 33,
    "regency_id": 3314,
    "district_id": 331420,
    "value": "Banyurip (Banyuurip)",
    "postal_code": "57256"
  },
  {
    "id": 331420,
    "province_id": 33,
    "regency_id": 3314,
    "district_id": 331420,
    "value": "Dawung",
    "postal_code": "57256"
  },
  {
    "id": 331420,
    "province_id": 33,
    "regency_id": 3314,
    "district_id": 331420,
    "value": "Japoh",
    "postal_code": "57256"
  },
  {
    "id": 331420,
    "province_id": 33,
    "regency_id": 3314,
    "district_id": 331420,
    "value": "Jenar",
    "postal_code": "57256"
  },
  {
    "id": 331420,
    "province_id": 33,
    "regency_id": 3314,
    "district_id": 331420,
    "value": "Kandangsapi (Kandang Sapi)",
    "postal_code": "57256"
  },
  {
    "id": 331420,
    "province_id": 33,
    "regency_id": 3314,
    "district_id": 331420,
    "value": "Mlale",
    "postal_code": "57256"
  },
  {
    "id": 331420,
    "province_id": 33,
    "regency_id": 3314,
    "district_id": 331420,
    "value": "Ngepringan",
    "postal_code": "57256"
  }
]