[
  {
    "id": 160511,
    "province_id": 16,
    "regency_id": 1605,
    "district_id": 160511,
    "value": "Batu Gane",
    "postal_code": "31625"
  },
  {
    "id": 160511,
    "province_id": 16,
    "regency_id": 1605,
    "district_id": 160511,
    "value": "Karang Panggung",
    "postal_code": "31625"
  },
  {
    "id": 160511,
    "province_id": 16,
    "regency_id": 1605,
    "district_id": 160511,
    "value": "Lubuk Ngin",
    "postal_code": "31625"
  },
  {
    "id": 160511,
    "province_id": 16,
    "regency_id": 1605,
    "district_id": 160511,
    "value": "Lubuk Ngin Baru",
    "postal_code": "31625"
  },
  {
    "id": 160511,
    "province_id": 16,
    "regency_id": 1605,
    "district_id": 160511,
    "value": "Muara Nilau",
    "postal_code": "31625"
  },
  {
    "id": 160511,
    "province_id": 16,
    "regency_id": 1605,
    "district_id": 160511,
    "value": "Napal Melintang",
    "postal_code": "31625"
  },
  {
    "id": 160511,
    "province_id": 16,
    "regency_id": 1605,
    "district_id": 160511,
    "value": "Prabu/Perabu Menang",
    "postal_code": "31625"
  },
  {
    "id": 160511,
    "province_id": 16,
    "regency_id": 1605,
    "district_id": 160511,
    "value": "Selangit",
    "postal_code": "31625"
  },
  {
    "id": 160511,
    "province_id": 16,
    "regency_id": 1605,
    "district_id": 160511,
    "value": "Taba Gindo",
    "postal_code": "31625"
  },
  {
    "id": 160511,
    "province_id": 16,
    "regency_id": 1605,
    "district_id": 160511,
    "value": "Taba Remanik",
    "postal_code": "31625"
  },
  {
    "id": 160511,
    "province_id": 16,
    "regency_id": 1605,
    "district_id": 160511,
    "value": "Taba Rena (Taba Renah)",
    "postal_code": "31625"
  },
  {
    "id": 160511,
    "province_id": 16,
    "regency_id": 1605,
    "district_id": 160511,
    "value": "Taba Tengah",
    "postal_code": "31625"
  }
]