[
  {
    "id": 740705,
    "province_id": 74,
    "regency_id": 7407,
    "district_id": 740705,
    "value": "Kabita",
    "postal_code": "93795"
  },
  {
    "id": 740705,
    "province_id": 74,
    "regency_id": 7407,
    "district_id": 740705,
    "value": "Kabita Togo",
    "postal_code": "93795"
  },
  {
    "id": 740705,
    "province_id": 74,
    "regency_id": 7407,
    "district_id": 740705,
    "value": "Kapota",
    "postal_code": "93795"
  },
  {
    "id": 740705,
    "province_id": 74,
    "regency_id": 7407,
    "district_id": 740705,
    "value": "Kapota Utara",
    "postal_code": "93795"
  },
  {
    "id": 740705,
    "province_id": 74,
    "regency_id": 7407,
    "district_id": 740705,
    "value": "Komala",
    "postal_code": "93795"
  },
  {
    "id": 740705,
    "province_id": 74,
    "regency_id": 7407,
    "district_id": 740705,
    "value": "Liya Bahari Indah",
    "postal_code": "93795"
  },
  {
    "id": 740705,
    "province_id": 74,
    "regency_id": 7407,
    "district_id": 740705,
    "value": "Liya Mawi (Liyamawi)",
    "postal_code": "93795"
  },
  {
    "id": 740705,
    "province_id": 74,
    "regency_id": 7407,
    "district_id": 740705,
    "value": "Liya Onemaelangka",
    "postal_code": "93795"
  },
  {
    "id": 740705,
    "province_id": 74,
    "regency_id": 7407,
    "district_id": 740705,
    "value": "Liya Togo",
    "postal_code": "93795"
  },
  {
    "id": 740705,
    "province_id": 74,
    "regency_id": 7407,
    "district_id": 740705,
    "value": "Mandati I",
    "postal_code": "93795"
  },
  {
    "id": 740705,
    "province_id": 74,
    "regency_id": 7407,
    "district_id": 740705,
    "value": "Mandati II",
    "postal_code": "93795"
  },
  {
    "id": 740705,
    "province_id": 74,
    "regency_id": 7407,
    "district_id": 740705,
    "value": "Mandati III",
    "postal_code": "93795"
  },
  {
    "id": 740705,
    "province_id": 74,
    "regency_id": 7407,
    "district_id": 740705,
    "value": "Matahora (Metohora)",
    "postal_code": "93795"
  },
  {
    "id": 740705,
    "province_id": 74,
    "regency_id": 7407,
    "district_id": 740705,
    "value": "Mola Bahari",
    "postal_code": "93795"
  },
  {
    "id": 740705,
    "province_id": 74,
    "regency_id": 7407,
    "district_id": 740705,
    "value": "Mola Nelayan Bhakti",
    "postal_code": "93795"
  },
  {
    "id": 740705,
    "province_id": 74,
    "regency_id": 7407,
    "district_id": 740705,
    "value": "Mola Samaturu",
    "postal_code": "93795"
  },
  {
    "id": 740705,
    "province_id": 74,
    "regency_id": 7407,
    "district_id": 740705,
    "value": "Mola Selatan",
    "postal_code": "93795"
  },
  {
    "id": 740705,
    "province_id": 74,
    "regency_id": 7407,
    "district_id": 740705,
    "value": "Mola Utara",
    "postal_code": "93795"
  },
  {
    "id": 740705,
    "province_id": 74,
    "regency_id": 7407,
    "district_id": 740705,
    "value": "Numana",
    "postal_code": "93795"
  },
  {
    "id": 740705,
    "province_id": 74,
    "regency_id": 7407,
    "district_id": 740705,
    "value": "Wisata Kolo (Wisata Koto)",
    "postal_code": "93795"
  },
  {
    "id": 740705,
    "province_id": 74,
    "regency_id": 7407,
    "district_id": 740705,
    "value": "Wungka",
    "postal_code": "93795"
  }
]