[
  {
    "id": 910609,
    "province_id": 91,
    "regency_id": 9106,
    "district_id": 910609,
    "value": "Aman",
    "postal_code": "98553"
  },
  {
    "id": 910609,
    "province_id": 91,
    "regency_id": 9106,
    "district_id": 910609,
    "value": "Amoi (Ammoy)",
    "postal_code": "98553"
  },
  {
    "id": 910609,
    "province_id": 91,
    "regency_id": 9106,
    "district_id": 910609,
    "value": "Biawer",
    "postal_code": "98553"
  },
  {
    "id": 910609,
    "province_id": 91,
    "regency_id": 9106,
    "district_id": 910609,
    "value": "Diano",
    "postal_code": "98553"
  },
  {
    "id": 910609,
    "province_id": 91,
    "regency_id": 9106,
    "district_id": 910609,
    "value": "Imbari",
    "postal_code": "98553"
  },
  {
    "id": 910609,
    "province_id": 91,
    "regency_id": 9106,
    "district_id": 910609,
    "value": "Inswambesi (Inswanbesi)",
    "postal_code": "98553"
  },
  {
    "id": 910609,
    "province_id": 91,
    "regency_id": 9106,
    "district_id": 910609,
    "value": "Inswambesi Sup (Inswanbesi Sup)",
    "postal_code": "98553"
  },
  {
    "id": 910609,
    "province_id": 91,
    "regency_id": 9106,
    "district_id": 910609,
    "value": "Inyobi",
    "postal_code": "98553"
  },
  {
    "id": 910609,
    "province_id": 91,
    "regency_id": 9106,
    "district_id": 910609,
    "value": "Karuiberik",
    "postal_code": "98553"
  },
  {
    "id": 910609,
    "province_id": 91,
    "regency_id": 9106,
    "district_id": 910609,
    "value": "Komboi (Komboy)",
    "postal_code": "98553"
  },
  {
    "id": 910609,
    "province_id": 91,
    "regency_id": 9106,
    "district_id": 910609,
    "value": "Koyomi",
    "postal_code": "98553"
  },
  {
    "id": 910609,
    "province_id": 91,
    "regency_id": 9106,
    "district_id": 910609,
    "value": "Mamfias",
    "postal_code": "98553"
  },
  {
    "id": 910609,
    "province_id": 91,
    "regency_id": 9106,
    "district_id": 910609,
    "value": "Manbeori",
    "postal_code": "98553"
  },
  {
    "id": 910609,
    "province_id": 91,
    "regency_id": 9106,
    "district_id": 910609,
    "value": "Maniri",
    "postal_code": "98553"
  },
  {
    "id": 910609,
    "province_id": 91,
    "regency_id": 9106,
    "district_id": 910609,
    "value": "Marur",
    "postal_code": "98553"
  },
  {
    "id": 910609,
    "province_id": 91,
    "regency_id": 9106,
    "district_id": 910609,
    "value": "Sawai (Saway)",
    "postal_code": "98553"
  },
  {
    "id": 910609,
    "province_id": 91,
    "regency_id": 9106,
    "district_id": 910609,
    "value": "Warawaf",
    "postal_code": "98553"
  },
  {
    "id": 910609,
    "province_id": 91,
    "regency_id": 9106,
    "district_id": 910609,
    "value": "Wasani",
    "postal_code": "98553"
  },
  {
    "id": 910609,
    "province_id": 91,
    "regency_id": 9106,
    "district_id": 910609,
    "value": "Wir Insos",
    "postal_code": "98553"
  },
  {
    "id": 910609,
    "province_id": 91,
    "regency_id": 9106,
    "district_id": 910609,
    "value": "Yeruboi (Yeruboy)",
    "postal_code": "98553"
  }
]