[
  {
    "id": 351706,
    "province_id": 35,
    "regency_id": 3517,
    "district_id": 351706,
    "value": "Betek",
    "postal_code": "61482"
  },
  {
    "id": 351706,
    "province_id": 35,
    "regency_id": 3517,
    "district_id": 351706,
    "value": "Dukuhdimoro",
    "postal_code": "61482"
  },
  {
    "id": 351706,
    "province_id": 35,
    "regency_id": 3517,
    "district_id": 351706,
    "value": "Dukuhmojo (Dukuh Mojo)",
    "postal_code": "61482"
  },
  {
    "id": 351706,
    "province_id": 35,
    "regency_id": 3517,
    "district_id": 351706,
    "value": "Gambiran",
    "postal_code": "61482"
  },
  {
    "id": 351706,
    "province_id": 35,
    "regency_id": 3517,
    "district_id": 351706,
    "value": "Janti",
    "postal_code": "61482"
  },
  {
    "id": 351706,
    "province_id": 35,
    "regency_id": 3517,
    "district_id": 351706,
    "value": "Johowinong",
    "postal_code": "61482"
  },
  {
    "id": 351706,
    "province_id": 35,
    "regency_id": 3517,
    "district_id": 351706,
    "value": "Kademangan",
    "postal_code": "61482"
  },
  {
    "id": 351706,
    "province_id": 35,
    "regency_id": 3517,
    "district_id": 351706,
    "value": "Karangwinongan",
    "postal_code": "61482"
  },
  {
    "id": 351706,
    "province_id": 35,
    "regency_id": 3517,
    "district_id": 351706,
    "value": "Karobelah",
    "postal_code": "61482"
  },
  {
    "id": 351706,
    "province_id": 35,
    "regency_id": 3517,
    "district_id": 351706,
    "value": "Kauman",
    "postal_code": "61482"
  },
  {
    "id": 351706,
    "province_id": 35,
    "regency_id": 3517,
    "district_id": 351706,
    "value": "Kedunglumpang",
    "postal_code": "61482"
  },
  {
    "id": 351706,
    "province_id": 35,
    "regency_id": 3517,
    "district_id": 351706,
    "value": "Mancilan",
    "postal_code": "61482"
  },
  {
    "id": 351706,
    "province_id": 35,
    "regency_id": 3517,
    "district_id": 351706,
    "value": "Miagan",
    "postal_code": "61482"
  },
  {
    "id": 351706,
    "province_id": 35,
    "regency_id": 3517,
    "district_id": 351706,
    "value": "Mojotrisno",
    "postal_code": "61482"
  },
  {
    "id": 351706,
    "province_id": 35,
    "regency_id": 3517,
    "district_id": 351706,
    "value": "Murukan",
    "postal_code": "61482"
  },
  {
    "id": 351706,
    "province_id": 35,
    "regency_id": 3517,
    "district_id": 351706,
    "value": "Seketi",
    "postal_code": "61482"
  },
  {
    "id": 351706,
    "province_id": 35,
    "regency_id": 3517,
    "district_id": 351706,
    "value": "Tanggalrejo",
    "postal_code": "61482"
  },
  {
    "id": 351706,
    "province_id": 35,
    "regency_id": 3517,
    "district_id": 351706,
    "value": "Tejo",
    "postal_code": "61482"
  }
]