[
  {
    "id": 732203,
    "province_id": 73,
    "regency_id": 7322,
    "district_id": 732203,
    "value": "Baliase",
    "postal_code": "92916"
  },
  {
    "id": 732203,
    "province_id": 73,
    "regency_id": 7322,
    "district_id": 732203,
    "value": "Baloli (Balebo)",
    "postal_code": "92912"
  },
  {
    "id": 732203,
    "province_id": 73,
    "regency_id": 7322,
    "district_id": 732203,
    "value": "Bone",
    "postal_code": "92914"
  },
  {
    "id": 732203,
    "province_id": 73,
    "regency_id": 7322,
    "district_id": 732203,
    "value": "Kamiri",
    "postal_code": "92961"
  },
  {
    "id": 732203,
    "province_id": 73,
    "regency_id": 7322,
    "district_id": 732203,
    "value": "Kappuna",
    "postal_code": "92913"
  },
  {
    "id": 732203,
    "province_id": 73,
    "regency_id": 7322,
    "district_id": 732203,
    "value": "Kasimbong",
    "postal_code": "92915"
  },
  {
    "id": 732203,
    "province_id": 73,
    "regency_id": 7322,
    "district_id": 732203,
    "value": "Laba",
    "postal_code": "92961"
  },
  {
    "id": 732203,
    "province_id": 73,
    "regency_id": 7322,
    "district_id": 732203,
    "value": "Lantang Tallang",
    "postal_code": "92961"
  },
  {
    "id": 732203,
    "province_id": 73,
    "regency_id": 7322,
    "district_id": 732203,
    "value": "Lapapa",
    "postal_code": "92961"
  },
  {
    "id": 732203,
    "province_id": 73,
    "regency_id": 7322,
    "district_id": 732203,
    "value": "Lero",
    "postal_code": "92961"
  },
  {
    "id": 732203,
    "province_id": 73,
    "regency_id": 7322,
    "district_id": 732203,
    "value": "Masamba",
    "postal_code": "92961"
  },
  {
    "id": 732203,
    "province_id": 73,
    "regency_id": 7322,
    "district_id": 732203,
    "value": "Pandak",
    "postal_code": "92961"
  },
  {
    "id": 732203,
    "province_id": 73,
    "regency_id": 7322,
    "district_id": 732203,
    "value": "Pincara",
    "postal_code": "92961"
  },
  {
    "id": 732203,
    "province_id": 73,
    "regency_id": 7322,
    "district_id": 732203,
    "value": "Pombakka",
    "postal_code": "92961"
  },
  {
    "id": 732203,
    "province_id": 73,
    "regency_id": 7322,
    "district_id": 732203,
    "value": "Pongo",
    "postal_code": "92961"
  },
  {
    "id": 732203,
    "province_id": 73,
    "regency_id": 7322,
    "district_id": 732203,
    "value": "Rompu",
    "postal_code": "92961"
  },
  {
    "id": 732203,
    "province_id": 73,
    "regency_id": 7322,
    "district_id": 732203,
    "value": "Sepakat",
    "postal_code": "92961"
  },
  {
    "id": 732203,
    "province_id": 73,
    "regency_id": 7322,
    "district_id": 732203,
    "value": "Sumilin (Sumillin)",
    "postal_code": "92961"
  },
  {
    "id": 732203,
    "province_id": 73,
    "regency_id": 7322,
    "district_id": 732203,
    "value": "Toradda (Torada)",
    "postal_code": "92961"
  }
]