[
  {
    "id": 330906,
    "province_id": 33,
    "regency_id": 3309,
    "district_id": 330906,
    "value": "Brajan",
    "postal_code": "57322"
  },
  {
    "id": 330906,
    "province_id": 33,
    "regency_id": 3309,
    "district_id": 330906,
    "value": "Butuh",
    "postal_code": "57322"
  },
  {
    "id": 330906,
    "province_id": 33,
    "regency_id": 3309,
    "district_id": 330906,
    "value": "Dlingo",
    "postal_code": "57322"
  },
  {
    "id": 330906,
    "province_id": 33,
    "regency_id": 3309,
    "district_id": 330906,
    "value": "Jurug",
    "postal_code": "57322"
  },
  {
    "id": 330906,
    "province_id": 33,
    "regency_id": 3309,
    "district_id": 330906,
    "value": "Karangnongko",
    "postal_code": "57322"
  },
  {
    "id": 330906,
    "province_id": 33,
    "regency_id": 3309,
    "district_id": 330906,
    "value": "Kemiri",
    "postal_code": "57321"
  },
  {
    "id": 330906,
    "province_id": 33,
    "regency_id": 3309,
    "district_id": 330906,
    "value": "Kragilan",
    "postal_code": "57323"
  },
  {
    "id": 330906,
    "province_id": 33,
    "regency_id": 3309,
    "district_id": 330906,
    "value": "Madu",
    "postal_code": "57322"
  },
  {
    "id": 330906,
    "province_id": 33,
    "regency_id": 3309,
    "district_id": 330906,
    "value": "Manggis",
    "postal_code": "57322"
  },
  {
    "id": 330906,
    "province_id": 33,
    "regency_id": 3309,
    "district_id": 330906,
    "value": "Metuk",
    "postal_code": "57322"
  },
  {
    "id": 330906,
    "province_id": 33,
    "regency_id": 3309,
    "district_id": 330906,
    "value": "Mojosongo",
    "postal_code": "57322"
  },
  {
    "id": 330906,
    "province_id": 33,
    "regency_id": 3309,
    "district_id": 330906,
    "value": "Singosari",
    "postal_code": "57322"
  },
  {
    "id": 330906,
    "province_id": 33,
    "regency_id": 3309,
    "district_id": 330906,
    "value": "Tambak",
    "postal_code": "57322"
  }
]