[
  {
    "id": 510304,
    "province_id": 51,
    "regency_id": 5103,
    "district_id": 510304,
    "value": "Belok/Sidan",
    "postal_code": "80353"
  },
  {
    "id": 510304,
    "province_id": 51,
    "regency_id": 5103,
    "district_id": 510304,
    "value": "Carangsari",
    "postal_code": "80353"
  },
  {
    "id": 510304,
    "province_id": 51,
    "regency_id": 5103,
    "district_id": 510304,
    "value": "Getasan",
    "postal_code": "80353"
  },
  {
    "id": 510304,
    "province_id": 51,
    "regency_id": 5103,
    "district_id": 510304,
    "value": "Pangsan",
    "postal_code": "80353"
  },
  {
    "id": 510304,
    "province_id": 51,
    "regency_id": 5103,
    "district_id": 510304,
    "value": "Pelaga",
    "postal_code": "80353"
  },
  {
    "id": 510304,
    "province_id": 51,
    "regency_id": 5103,
    "district_id": 510304,
    "value": "Petang",
    "postal_code": "80353"
  },
  {
    "id": 510304,
    "province_id": 51,
    "regency_id": 5103,
    "district_id": 510304,
    "value": "Sulangai",
    "postal_code": "80353"
  }
]