[
  {
    "id": 170206,
    "province_id": 17,
    "regency_id": 1702,
    "district_id": 170206,
    "value": "Bedeng SS",
    "postal_code": "39183"
  },
  {
    "id": 170206,
    "province_id": 17,
    "regency_id": 1702,
    "district_id": 170206,
    "value": "Derati",
    "postal_code": "39183"
  },
  {
    "id": 170206,
    "province_id": 17,
    "regency_id": 1702,
    "district_id": 170206,
    "value": "Durian Mas",
    "postal_code": "39183"
  },
  {
    "id": 170206,
    "province_id": 17,
    "regency_id": 1702,
    "district_id": 170206,
    "value": "Dusun Baru",
    "postal_code": "39183"
  },
  {
    "id": 170206,
    "province_id": 17,
    "regency_id": 1702,
    "district_id": 170206,
    "value": "Kota Padang",
    "postal_code": "39183"
  },
  {
    "id": 170206,
    "province_id": 17,
    "regency_id": 1702,
    "district_id": 170206,
    "value": "Kota Padang Baru",
    "postal_code": "39183"
  },
  {
    "id": 170206,
    "province_id": 17,
    "regency_id": 1702,
    "district_id": 170206,
    "value": "Lubuk Mumpo",
    "postal_code": "39183"
  },
  {
    "id": 170206,
    "province_id": 17,
    "regency_id": 1702,
    "district_id": 170206,
    "value": "Suka Rami",
    "postal_code": "39183"
  },
  {
    "id": 170206,
    "province_id": 17,
    "regency_id": 1702,
    "district_id": 170206,
    "value": "Taba Anyar",
    "postal_code": "39183"
  },
  {
    "id": 170206,
    "province_id": 17,
    "regency_id": 1702,
    "district_id": 170206,
    "value": "Tanjung Gelang",
    "postal_code": "39183"
  }
]