[
  {
    "id": 160510,
    "province_id": 16,
    "regency_id": 1605,
    "district_id": 160510,
    "value": "Babat",
    "postal_code": "30771"
  },
  {
    "id": 160510,
    "province_id": 16,
    "regency_id": 1605,
    "district_id": 160510,
    "value": "Kosgoro",
    "postal_code": "30771"
  },
  {
    "id": 160510,
    "province_id": 16,
    "regency_id": 1605,
    "district_id": 160510,
    "value": "Paduraksa",
    "postal_code": "30771"
  },
  {
    "id": 160510,
    "province_id": 16,
    "regency_id": 1605,
    "district_id": 160510,
    "value": "Pasenan",
    "postal_code": "30771"
  },
  {
    "id": 160510,
    "province_id": 16,
    "regency_id": 1605,
    "district_id": 160510,
    "value": "Sri Mulyo",
    "postal_code": "30771"
  },
  {
    "id": 160510,
    "province_id": 16,
    "regency_id": 1605,
    "district_id": 160510,
    "value": "Suka Karya (Sukakarya)",
    "postal_code": "30771"
  },
  {
    "id": 160510,
    "province_id": 16,
    "regency_id": 1605,
    "district_id": 160510,
    "value": "Sukamana",
    "postal_code": "30771"
  },
  {
    "id": 160510,
    "province_id": 16,
    "regency_id": 1605,
    "district_id": 160510,
    "value": "Sukamerindu",
    "postal_code": "30771"
  },
  {
    "id": 160510,
    "province_id": 16,
    "regency_id": 1605,
    "district_id": 160510,
    "value": "Sukaraya",
    "postal_code": "30771"
  },
  {
    "id": 160510,
    "province_id": 16,
    "regency_id": 1605,
    "district_id": 160510,
    "value": "Sukaraya Baru",
    "postal_code": "30771"
  },
  {
    "id": 160510,
    "province_id": 16,
    "regency_id": 1605,
    "district_id": 160510,
    "value": "Suko Rejo (Sukarejo)",
    "postal_code": "30771"
  },
  {
    "id": 160510,
    "province_id": 16,
    "regency_id": 1605,
    "district_id": 160510,
    "value": "Sumber Karya",
    "postal_code": "30771"
  },
  {
    "id": 160510,
    "province_id": 16,
    "regency_id": 1605,
    "district_id": 160510,
    "value": "Terawas",
    "postal_code": "30771"
  }
]