[
  {
    "id": 531605,
    "province_id": 53,
    "regency_id": 5316,
    "district_id": 531605,
    "value": "Anakoli",
    "postal_code": "86471"
  },
  {
    "id": 531605,
    "province_id": 53,
    "regency_id": 5316,
    "district_id": 531605,
    "value": "Natatoto",
    "postal_code": "86471"
  },
  {
    "id": 531605,
    "province_id": 53,
    "regency_id": 5316,
    "district_id": 531605,
    "value": "Tendakinde (Tenda Kinde)",
    "postal_code": "86471"
  },
  {
    "id": 531605,
    "province_id": 53,
    "regency_id": 5316,
    "district_id": 531605,
    "value": "Tendatoto",
    "postal_code": "86471"
  },
  {
    "id": 531605,
    "province_id": 53,
    "regency_id": 5316,
    "district_id": 531605,
    "value": "Totomala",
    "postal_code": "86471"
  }
]