[
  {
    "id": 760601,
    "province_id": 76,
    "regency_id": 7606,
    "district_id": 760601,
    "value": "Bambadaru",
    "postal_code": "91463"
  },
  {
    "id": 760601,
    "province_id": 76,
    "regency_id": 7606,
    "district_id": 760601,
    "value": "Batu Parigi",
    "postal_code": "91463"
  },
  {
    "id": 760601,
    "province_id": 76,
    "regency_id": 7606,
    "district_id": 760601,
    "value": "Mahahe",
    "postal_code": "91463"
  },
  {
    "id": 760601,
    "province_id": 76,
    "regency_id": 7606,
    "district_id": 760601,
    "value": "Palongaan (Polongaan)",
    "postal_code": "91463"
  },
  {
    "id": 760601,
    "province_id": 76,
    "regency_id": 7606,
    "district_id": 760601,
    "value": "Saloadak",
    "postal_code": "91463"
  },
  {
    "id": 760601,
    "province_id": 76,
    "regency_id": 7606,
    "district_id": 760601,
    "value": "Salobaja (Sulobaja)",
    "postal_code": "91463"
  },
  {
    "id": 760601,
    "province_id": 76,
    "regency_id": 7606,
    "district_id": 760601,
    "value": "Sejati",
    "postal_code": "91463"
  },
  {
    "id": 760601,
    "province_id": 76,
    "regency_id": 7606,
    "district_id": 760601,
    "value": "Tobadak",
    "postal_code": "91463"
  }
]