[
  {
    "id": 720709,
    "province_id": 72,
    "regency_id": 7207,
    "district_id": 720709,
    "value": "Alasan Nggolobuton",
    "postal_code": "94882"
  },
  {
    "id": 720709,
    "province_id": 72,
    "regency_id": 7207,
    "district_id": 720709,
    "value": "Babang",
    "postal_code": "94882"
  },
  {
    "id": 720709,
    "province_id": 72,
    "regency_id": 7207,
    "district_id": 720709,
    "value": "Balalon",
    "postal_code": "94882"
  },
  {
    "id": 720709,
    "province_id": 72,
    "regency_id": 7207,
    "district_id": 720709,
    "value": "Boluni",
    "postal_code": "94882"
  },
  {
    "id": 720709,
    "province_id": 72,
    "regency_id": 7207,
    "district_id": 720709,
    "value": "Bonepuso",
    "postal_code": "94882"
  },
  {
    "id": 720709,
    "province_id": 72,
    "regency_id": 7207,
    "district_id": 720709,
    "value": "Labotankandi (Labotakandi)",
    "postal_code": "94882"
  },
  {
    "id": 720709,
    "province_id": 72,
    "regency_id": 7207,
    "district_id": 720709,
    "value": "Lemelu",
    "postal_code": "94882"
  },
  {
    "id": 720709,
    "province_id": 72,
    "regency_id": 7207,
    "district_id": 720709,
    "value": "Lolantang",
    "postal_code": "94882"
  },
  {
    "id": 720709,
    "province_id": 72,
    "regency_id": 7207,
    "district_id": 720709,
    "value": "Mangais",
    "postal_code": "94882"
  },
  {
    "id": 720709,
    "province_id": 72,
    "regency_id": 7207,
    "district_id": 720709,
    "value": "Momotan",
    "postal_code": "94882"
  },
  {
    "id": 720709,
    "province_id": 72,
    "regency_id": 7207,
    "district_id": 720709,
    "value": "Osan",
    "postal_code": "94882"
  },
  {
    "id": 720709,
    "province_id": 72,
    "regency_id": 7207,
    "district_id": 720709,
    "value": "Palabatu I (Palabatu Satu)",
    "postal_code": "94882"
  },
  {
    "id": 720709,
    "province_id": 72,
    "regency_id": 7207,
    "district_id": 720709,
    "value": "Palabatu II (Palabatu Dua)",
    "postal_code": "94882"
  },
  {
    "id": 720709,
    "province_id": 72,
    "regency_id": 7207,
    "district_id": 720709,
    "value": "Pandaluk",
    "postal_code": "94882"
  },
  {
    "id": 720709,
    "province_id": 72,
    "regency_id": 7207,
    "district_id": 720709,
    "value": "Pipilogot Paipaisu",
    "postal_code": "94882"
  },
  {
    "id": 720709,
    "province_id": 72,
    "regency_id": 7207,
    "district_id": 720709,
    "value": "Sabelak",
    "postal_code": "94882"
  },
  {
    "id": 720709,
    "province_id": 72,
    "regency_id": 7207,
    "district_id": 720709,
    "value": "Suit",
    "postal_code": "94882"
  },
  {
    "id": 720709,
    "province_id": 72,
    "regency_id": 7207,
    "district_id": 720709,
    "value": "Tatarandang",
    "postal_code": "94882"
  },
  {
    "id": 720709,
    "province_id": 72,
    "regency_id": 7207,
    "district_id": 720709,
    "value": "Toi-Toi (Toy-Toy)",
    "postal_code": "94882"
  },
  {
    "id": 720709,
    "province_id": 72,
    "regency_id": 7207,
    "district_id": 720709,
    "value": "Unu",
    "postal_code": "94882"
  }
]