[
  {
    "id": 350205,
    "province_id": 35,
    "regency_id": 3502,
    "district_id": 350205,
    "value": "Bondrang",
    "postal_code": "63475"
  },
  {
    "id": 350205,
    "province_id": 35,
    "regency_id": 3502,
    "district_id": 350205,
    "value": "Grogol",
    "postal_code": "63475"
  },
  {
    "id": 350205,
    "province_id": 35,
    "regency_id": 3502,
    "district_id": 350205,
    "value": "Ketro",
    "postal_code": "63475"
  },
  {
    "id": 350205,
    "province_id": 35,
    "regency_id": 3502,
    "district_id": 350205,
    "value": "Kori",
    "postal_code": "63475"
  },
  {
    "id": 350205,
    "province_id": 35,
    "regency_id": 3502,
    "district_id": 350205,
    "value": "Ngindeng",
    "postal_code": "63475"
  },
  {
    "id": 350205,
    "province_id": 35,
    "regency_id": 3502,
    "district_id": 350205,
    "value": "Pangkal",
    "postal_code": "63475"
  },
  {
    "id": 350205,
    "province_id": 35,
    "regency_id": 3502,
    "district_id": 350205,
    "value": "Prayungan",
    "postal_code": "63475"
  },
  {
    "id": 350205,
    "province_id": 35,
    "regency_id": 3502,
    "district_id": 350205,
    "value": "Sawoo",
    "postal_code": "63475"
  },
  {
    "id": 350205,
    "province_id": 35,
    "regency_id": 3502,
    "district_id": 350205,
    "value": "Sriti (Serinti)",
    "postal_code": "63475"
  },
  {
    "id": 350205,
    "province_id": 35,
    "regency_id": 3502,
    "district_id": 350205,
    "value": "Temon",
    "postal_code": "63475"
  },
  {
    "id": 350205,
    "province_id": 35,
    "regency_id": 3502,
    "district_id": 350205,
    "value": "Tempuran",
    "postal_code": "63475"
  },
  {
    "id": 350205,
    "province_id": 35,
    "regency_id": 3502,
    "district_id": 350205,
    "value": "Tugurejo",
    "postal_code": "63475"
  },
  {
    "id": 350205,
    "province_id": 35,
    "regency_id": 3502,
    "district_id": 350205,
    "value": "Tumpak Pelem (Tumpakpelem)",
    "postal_code": "63475"
  },
  {
    "id": 350205,
    "province_id": 35,
    "regency_id": 3502,
    "district_id": 350205,
    "value": "Tumpuk",
    "postal_code": "63475"
  }
]