[
  {
    "id": 321123,
    "province_id": 32,
    "regency_id": 3211,
    "district_id": 321123,
    "value": "Bantarmara",
    "postal_code": "45355"
  },
  {
    "id": 321123,
    "province_id": 32,
    "regency_id": 3211,
    "district_id": 321123,
    "value": "Cimara",
    "postal_code": "45355"
  },
  {
    "id": 321123,
    "province_id": 32,
    "regency_id": 3211,
    "district_id": 321123,
    "value": "Cipandanwangi",
    "postal_code": "45355"
  },
  {
    "id": 321123,
    "province_id": 32,
    "regency_id": 3211,
    "district_id": 321123,
    "value": "Cisalak",
    "postal_code": "45355"
  },
  {
    "id": 321123,
    "province_id": 32,
    "regency_id": 3211,
    "district_id": 321123,
    "value": "Cisarua",
    "postal_code": "45355"
  },
  {
    "id": 321123,
    "province_id": 32,
    "regency_id": 3211,
    "district_id": 321123,
    "value": "Ciuyah",
    "postal_code": "45355"
  },
  {
    "id": 321123,
    "province_id": 32,
    "regency_id": 3211,
    "district_id": 321123,
    "value": "Kebonkalapa",
    "postal_code": "45355"
  }
]