[
  {
    "id": 950226,
    "province_id": 95,
    "regency_id": 9502,
    "district_id": 950226,
    "value": "Bakata",
    "postal_code": "99441"
  },
  {
    "id": 950226,
    "province_id": 95,
    "regency_id": 9502,
    "district_id": 950226,
    "value": "Batani",
    "postal_code": "99441"
  },
  {
    "id": 950226,
    "province_id": 95,
    "regency_id": 9502,
    "district_id": 950226,
    "value": "Karye / Kariye",
    "postal_code": "99441"
  },
  {
    "id": 950226,
    "province_id": 95,
    "regency_id": 9502,
    "district_id": 950226,
    "value": "Palur Dua",
    "postal_code": "99441"
  },
  {
    "id": 950226,
    "province_id": 95,
    "regency_id": 9502,
    "district_id": 950226,
    "value": "Palur Satu",
    "postal_code": "99441"
  },
  {
    "id": 950226,
    "province_id": 95,
    "regency_id": 9502,
    "district_id": 950226,
    "value": "Segame",
    "postal_code": "99441"
  },
  {
    "id": 950226,
    "province_id": 95,
    "regency_id": 9502,
    "district_id": 950226,
    "value": "Sople",
    "postal_code": "99441"
  }
]